README.md
setup.py
jeeva/__init__.py
jeeva/jeeva.py
jeeva/sample.py
jeeva.egg-info/PKG-INFO
jeeva.egg-info/SOURCES.txt
jeeva.egg-info/dependency_links.txt
jeeva.egg-info/entry_points.txt
jeeva.egg-info/requires.txt
jeeva.egg-info/top_level.txt