Metadata-Version: 1.1
Name: jeeva
Version: 0.1.0
Summary: A handy application of web scrapping along with Named entity recognition.
Home-page: UNKNOWN
Author: Jeevanantham V
Author-email: jeevanantham.v26@gmail.com
License: UNKNOWN
Platform: UNKNOWN
Classifier: Programming Language :: Python :: 3
